openproficiency/Topic.py
openproficiency/TopicList.py
openproficiency/__init__.py
openproficiency-0.0.1.dist-info/licenses/LICENSE
openproficiency-0.0.1.dist-info/METADATA
openproficiency-0.0.1.dist-info/WHEEL
openproficiency-0.0.1.dist-info/top_level.txt
openproficiency-0.0.1.dist-info/RECORD
