Metadata-Version: 2.4
Name: openproficiency
Version: 0.0.1
Summary: A simple library for managing proficiency topics and topic lists
Home-page: https://github.com/openproficiency/openproficiency
Author: OpenProficiency Contributors
Author-email: "Christopher W. Blake" <chriswblake@gmail.com>
License: MIT
Project-URL: Homepage, https://github.com/openproficiency
Project-URL: Documentation, https://github.com/openproficiency/model
Project-URL: Repository, https://github.com/openproficiency/python-sdk.git
Project-URL: Issues, https://github.com/openproficiency/python-sdk/issues
Keywords: topic,topic list,proficiency,learning,knowledge
Classifier: Development Status :: 3 - Alpha
Classifier: Intended Audience :: Developers
Classifier: License :: OSI Approved :: MIT License
Classifier: Programming Language :: Python :: 3
Classifier: Programming Language :: Python :: 3.10
Classifier: Programming Language :: Python :: 3.11
Classifier: Programming Language :: Python :: 3.12
Classifier: Programming Language :: Python :: 3.13
Classifier: Programming Language :: Python :: 3.14
Requires-Python: >=3.8
License-File: LICENSE
Dynamic: author
Dynamic: home-page
Dynamic: license-file
Dynamic: requires-python
